ezanchor/__init__.py
ezanchor/anchor.py
ezanchor/equipment.py
ezanchor/plotter.py
ezanchor-1.1.0.dist-info/METADATA
ezanchor-1.1.0.dist-info/WHEEL
ezanchor-1.1.0.dist-info/licenses/LICENSE
ezanchor-1.1.0.dist-info/RECORD
