Metadata-Version: 2.4
Name: ezanchor
Version: 1.1.0
Summary: Nonstructural Component Anchorage Calculation
Project-URL: Homepage, https://github.com/wcfrobert/ezanchor
Project-URL: Bug Tracker, https://github.com/wcfrobert/ezanchor/issues
Author-email: wcfrobert <temprobertdev@gmail.com>
License-File: LICENSE
Keywords: anchorage,nonstructural,seismic force,structural engineering
Classifier: License :: OSI Approved :: MIT License
Classifier: Operating System :: OS Independent
Classifier: Programming Language :: Python :: 3
Requires-Python: >=3.7
Requires-Dist: matplotlib>=3.7.1
Requires-Dist: numpy>=1.24.3
